{
  "lastUpdated": "2026-01-25T16:50:33.360535+00:00",
  "kcps": {
    "metar": "KCPS 251610Z 35014G22KT 1 1/2SM -SN BKN028 BKN036 OVC045 M13/M16 A3014 RMK AO2 P0000 T11281161 $",
    "windDirection": 350,
    "windSpeed": 14,
    "windGust": 22,
    "visibility": 0.5,
    "temperatureC": -13,
    "dewPointC": -16,
    "cloudCeiling": 2800,
    "altimeter": "A3014",
    "timestamp": "2026-01-25T16:10:00+00:00",
    "station": "KCPS"
  },
  "kstl": {
    "metar": "KSTL 251643Z 35013KT 3SM -SN BKN035 OVC044 M13/M17 A3013 RMK AO2 P0000 T11331167 $",
    "windDirection": 350,
    "windSpeed": 13,
    "windGust": null,
    "visibility": 3,
    "temperatureC": -13,
    "dewPointC": -17,
    "cloudCeiling": 3500,
    "altimeter": "A3013",
    "timestamp": "2026-01-25T16:43:00+00:00",
    "station": "KSTL"
  }
}