{
  "lastUpdated": "2025-11-20T04:36:41.664307+00:00",
  "kcps": {
    "metar": "KCPS 200253Z 11003KT 7SM OVC008 09/07 A3019 RMK AO2 SLP225 T00890072 51000",
    "windDirection": 110,
    "windSpeed": 3,
    "windGust": null,
    "visibility": 7,
    "temperatureC": 9,
    "dewPointC": 7,
    "cloudCeiling": 800,
    "altimeter": "A3019",
    "timestamp": "2025-11-20T02:53:00+00:00",
    "station": "KCPS"
  },
  "kstl": {
    "metar": "KSTL 200358Z 11005KT 5SM BR OVC008 09/07 A3018 RMK AO2 T00890072 $",
    "windDirection": 110,
    "windSpeed": 5,
    "windGust": null,
    "visibility": 5,
    "temperatureC": 9,
    "dewPointC": 7,
    "cloudCeiling": 800,
    "altimeter": "A3018",
    "timestamp": "2025-11-20T03:58:00+00:00",
    "station": "KSTL"
  }
}