{
  "lastUpdated": "2025-12-01T12:44:27.697880+00:00",
  "kcps": {
    "metar": "KCPS 011153Z AUTO 09004KT 10SM OVC023 M05/M08 A3043 RMK AO2 SLP308 T10501078 11044 21050 56022 $",
    "windDirection": 90,
    "windSpeed": 4,
    "windGust": null,
    "visibility": 10,
    "temperatureC": -5,
    "dewPointC": -8,
    "cloudCeiling": 2300,
    "altimeter": "A3043",
    "timestamp": "2025-12-01T11:53:00+00:00",
    "station": "KCPS"
  },
  "kstl": {
    "metar": "KSTL 011213Z 10006KT 10SM BKN021 OVC110 M05/M08 A3042 RMK AO2 T10501078 $",
    "windDirection": 100,
    "windSpeed": 6,
    "windGust": null,
    "visibility": 10,
    "temperatureC": -5,
    "dewPointC": -8,
    "cloudCeiling": 2100,
    "altimeter": "A3042",
    "timestamp": "2025-12-01T12:13:00+00:00",
    "station": "KSTL"
  }
}