{
  "lastUpdated": "2026-02-27T17:17:06.637247+00:00",
  "kcps": {
    "metar": "KCPS 271653Z 21006KT 10SM CLR 17/06 A2997 RMK AO2 SLP150 T01670061 $",
    "windDirection": 210,
    "windSpeed": 6,
    "windGust": null,
    "visibility": 10,
    "temperatureC": 17,
    "dewPointC": 6,
    "cloudCeiling": 99999,
    "altimeter": "A2997",
    "timestamp": "2026-02-27T16:53:00+00:00",
    "station": "KCPS"
  },
  "kstl": {
    "metar": "KSTL 271651Z 23011KT 10SM FEW250 18/02 A2997 RMK AO2 SLP148 T01830022 $",
    "windDirection": 230,
    "windSpeed": 11,
    "windGust": null,
    "visibility": 10,
    "temperatureC": 18,
    "dewPointC": 2,
    "cloudCeiling": null,
    "altimeter": "A2997",
    "timestamp": "2026-02-27T16:51:00+00:00",
    "station": "KSTL"
  }
}